acparser/__init__.py
acparser-1.0.0.dist-info/entry_points.txt
acparser-1.0.0.dist-info/licenses/LICENSE
acparser-1.0.0.dist-info/WHEEL
acparser-1.0.0.dist-info/METADATA
acparser-1.0.0.dist-info/RECORD
