Metadata-Version: 2.4
Name: acparser
Version: 1.0.0
Summary: Ansible collection parser for developers.
Author-email: Anwesha Das <anwesha.srkr@gmail.com>
License-Expression: GPL-3.0-or-later
License-File: LICENSE
Requires-Dist: pyyaml
Requires-Dist: packaging
Requires-Dist: identify[license]
Requires-Dist: requirements-parser
Project-URL: Home, https://github.com/anweshadas/acparser
